megadexserver
