Metadata-Version: 1.0
Name: megadexserver
Version: 0.0.5
Summary: Mega Indexer Server
Home-page: https://github.com/hodgesds/megadex-server
Author: Daniel Hodges
Author-email: hodges.daniel.scott@gmail.com
License: UNKNOWN
Platform: UNKNOWN
